{
    "file": [
        {
            "fid": [
                {
                    "value": 1
                }
            ],
            "uuid": [
                {
                    "value": "0ba2058f-967a-4dfc-a063-63dea444a150"
                }
            ],
            "langcode": [
                {
                    "value": "en"
                }
            ],
            "uid": [
                {
                    "target_id": 37
                }
            ],
            "filename": [
                {
                    "value": "R-2879-1236035472.jpeg.jpg"
                }
            ],
            "uri": [
                {
                    "value": "public:\/\/2020-05\/R-2879-1236035472.jpeg.jpg",
                    "url": "\/sites\/default\/files\/2020-05\/R-2879-1236035472.jpeg.jpg"
                }
            ],
            "filemime": [
                {
                    "value": "image\/jpeg"
                }
            ],
            "filesize": [
                {
                    "value": 55323
                }
            ],
            "status": [
                {
                    "value": true
                }
            ],
            "created": [
                {
                    "value": "2020-05-06T11:37:15+00:00",
                    "format": "Y-m-d\\TH:i:sP"
                }
            ],
            "changed": [
                {
                    "value": "2020-05-06T11:37:20+00:00",
                    "format": "Y-m-d\\TH:i:sP"
                }
            ]
        },
        {
            "fid": [
                {
                    "value": 2
                }
            ],
            "uuid": [
                {
                    "value": "afe19b28-7f85-4d2f-b144-07c531ce8c2e"
                }
            ],
            "langcode": [
                {
                    "value": "en"
                }
            ],
            "uid": [
                {
                    "target_id": 37
                }
            ],
            "filename": [
                {
                    "value": "pexels-photo-414171.jpeg"
                }
            ],
            "uri": [
                {
                    "value": "public:\/\/2020-05\/pexels-photo-414171.jpeg",
                    "url": "\/sites\/default\/files\/2020-05\/pexels-photo-414171.jpeg"
                }
            ],
            "filemime": [
                {
                    "value": "image\/jpeg"
                }
            ],
            "filesize": [
                {
                    "value": 17663
                }
            ],
            "status": [
                {
                    "value": true
                }
            ],
            "created": [
                {
                    "value": "2020-05-06T11:40:02+00:00",
                    "format": "Y-m-d\\TH:i:sP"
                }
            ],
            "changed": [
                {
                    "value": "2020-05-06T11:40:08+00:00",
                    "format": "Y-m-d\\TH:i:sP"
                }
            ]
        },
        {
            "fid": [
                {
                    "value": 3
                }
            ],
            "uuid": [
                {
                    "value": "bab43a7c-7ecf-40f9-9898-b6760dea2cbf"
                }
            ],
            "langcode": [
                {
                    "value": "en"
                }
            ],
            "uid": [
                {
                    "target_id": 37
                }
            ],
            "filename": [
                {
                    "value": "1200px-Mona_Lisa-restored.jpg"
                }
            ],
            "uri": [
                {
                    "value": "public:\/\/2020-05\/1200px-Mona_Lisa-restored.jpg",
                    "url": "\/sites\/default\/files\/2020-05\/1200px-Mona_Lisa-restored.jpg"
                }
            ],
            "filemime": [
                {
                    "value": "image\/jpeg"
                }
            ],
            "filesize": [
                {
                    "value": 557138
                }
            ],
            "status": [
                {
                    "value": true
                }
            ],
            "created": [
                {
                    "value": "2020-05-06T11:40:13+00:00",
                    "format": "Y-m-d\\TH:i:sP"
                }
            ],
            "changed": [
                {
                    "value": "2020-05-06T11:40:18+00:00",
                    "format": "Y-m-d\\TH:i:sP"
                }
            ]
        },
        {
            "fid": [
                {
                    "value": 4
                }
            ],
            "uuid": [
                {
                    "value": "bce337ab-8b99-415c-b4e4-1a08d2ab656b"
                }
            ],
            "langcode": [
                {
                    "value": "en"
                }
            ],
            "uid": [
                {
                    "target_id": 512
                }
            ],
            "filename": [
                {
                    "value": "promo-0.png"
                }
            ],
            "uri": [
                {
                    "value": "public:\/\/2020-04\/promo-0.png",
                    "url": "\/sites\/default\/files\/2020-04\/promo-0.png"
                }
            ],
            "filemime": [
                {
                    "value": "image\/png"
                }
            ],
            "filesize": [
                {
                    "value": 20191
                }
            ],
            "status": [
                {
                    "value": true
                }
            ],
            "created": [
                {
                    "value": "2020-04-21T09:43:20+00:00",
                    "format": "Y-m-d\\TH:i:sP"
                }
            ],
            "changed": [
                {
                    "value": "2020-04-21T09:43:28+00:00",
                    "format": "Y-m-d\\TH:i:sP"
                }
            ]
        },
        {
            "fid": [
                {
                    "value": 5
                }
            ],
            "uuid": [
                {
                    "value": "83a6a636-7726-43fb-b376-8f4ff8785ba7"
                }
            ],
            "langcode": [
                {
                    "value": "en"
                }
            ],
            "uid": [
                {
                    "target_id": 512
                }
            ],
            "filename": [
                {
                    "value": "promo-1.png"
                }
            ],
            "uri": [
                {
                    "value": "public:\/\/2020-04\/promo-1.png",
                    "url": "\/sites\/default\/files\/2020-04\/promo-1.png"
                }
            ],
            "filemime": [
                {
                    "value": "image\/png"
                }
            ],
            "filesize": [
                {
                    "value": 42054
                }
            ],
            "status": [
                {
                    "value": true
                }
            ],
            "created": [
                {
                    "value": "2020-04-21T09:44:08+00:00",
                    "format": "Y-m-d\\TH:i:sP"
                }
            ],
            "changed": [
                {
                    "value": "2020-04-21T09:44:14+00:00",
                    "format": "Y-m-d\\TH:i:sP"
                }
            ]
        },
        {
            "fid": [
                {
                    "value": 6
                }
            ],
            "uuid": [
                {
                    "value": "5d6b1a0e-a67b-4fc4-8904-09e55f0a55cb"
                }
            ],
            "langcode": [
                {
                    "value": "en"
                }
            ],
            "uid": [
                {
                    "target_id": 512
                }
            ],
            "filename": [
                {
                    "value": "promo-2.png"
                }
            ],
            "uri": [
                {
                    "value": "public:\/\/2020-04\/promo-2.png",
                    "url": "\/sites\/default\/files\/2020-04\/promo-2.png"
                }
            ],
            "filemime": [
                {
                    "value": "image\/png"
                }
            ],
            "filesize": [
                {
                    "value": 48171
                }
            ],
            "status": [
                {
                    "value": true
                }
            ],
            "created": [
                {
                    "value": "2020-04-21T09:44:51+00:00",
                    "format": "Y-m-d\\TH:i:sP"
                }
            ],
            "changed": [
                {
                    "value": "2020-04-21T09:44:57+00:00",
                    "format": "Y-m-d\\TH:i:sP"
                }
            ]
        },
        {
            "fid": [
                {
                    "value": 7
                }
            ],
            "uuid": [
                {
                    "value": "87fdf3b4-7aea-4a12-840d-d841e8d82d3f"
                }
            ],
            "langcode": [
                {
                    "value": "en"
                }
            ],
            "uid": [
                {
                    "target_id": 512
                }
            ],
            "filename": [
                {
                    "value": "promo-3.png"
                }
            ],
            "uri": [
                {
                    "value": "public:\/\/2020-04\/promo-3.png",
                    "url": "\/sites\/default\/files\/2020-04\/promo-3.png"
                }
            ],
            "filemime": [
                {
                    "value": "image\/png"
                }
            ],
            "filesize": [
                {
                    "value": 27951
                }
            ],
            "status": [
                {
                    "value": true
                }
            ],
            "created": [
                {
                    "value": "2020-04-21T09:45:38+00:00",
                    "format": "Y-m-d\\TH:i:sP"
                }
            ],
            "changed": [
                {
                    "value": "2020-04-21T09:45:44+00:00",
                    "format": "Y-m-d\\TH:i:sP"
                }
            ]
        },
        {
            "fid": [
                {
                    "value": 8
                }
            ],
            "uuid": [
                {
                    "value": "8e136d39-33e9-4508-8431-b6bf9ea7ccef"
                }
            ],
            "langcode": [
                {
                    "value": "en"
                }
            ],
            "uid": [
                {
                    "target_id": 2
                }
            ],
            "filename": [
                {
                    "value": "orange-county-courthouse11_2.jpg"
                }
            ],
            "uri": [
                {
                    "value": "public:\/\/2020-03\/orange-county-courthouse11_2.jpg",
                    "url": "\/sites\/default\/files\/2020-03\/orange-county-courthouse11_2.jpg"
                }
            ],
            "filemime": [
                {
                    "value": "image\/jpeg"
                }
            ],
            "filesize": [
                {
                    "value": 284177
                }
            ],
            "status": [
                {
                    "value": true
                }
            ],
            "created": [
                {
                    "value": "2020-03-15T21:17:50+00:00",
                    "format": "Y-m-d\\TH:i:sP"
                }
            ],
            "changed": [
                {
                    "value": "2020-03-15T21:17:53+00:00",
                    "format": "Y-m-d\\TH:i:sP"
                }
            ]
        },
        {
            "fid": [
                {
                    "value": 9
                }
            ],
            "uuid": [
                {
                    "value": "6778891e-3670-49cd-816f-be38e2db5182"
                }
            ],
            "langcode": [
                {
                    "value": "en"
                }
            ],
            "uid": [
                {
                    "target_id": 2
                }
            ],
            "filename": [
                {
                    "value": "CAS_2.jpg"
                }
            ],
            "uri": [
                {
                    "value": "public:\/\/2020-03\/CAS_2.jpg",
                    "url": "\/sites\/default\/files\/2020-03\/CAS_2.jpg"
                }
            ],
            "filemime": [
                {
                    "value": "image\/jpeg"
                }
            ],
            "filesize": [
                {
                    "value": 292455
                }
            ],
            "status": [
                {
                    "value": true
                }
            ],
            "created": [
                {
                    "value": "2020-03-15T21:18:03+00:00",
                    "format": "Y-m-d\\TH:i:sP"
                }
            ],
            "changed": [
                {
                    "value": "2020-03-15T21:18:08+00:00",
                    "format": "Y-m-d\\TH:i:sP"
                }
            ]
        },
        {
            "fid": [
                {
                    "value": 10
                }
            ],
            "uuid": [
                {
                    "value": "75d34d64-0c82-42ac-bb80-a69b34600a83"
                }
            ],
            "langcode": [
                {
                    "value": "en"
                }
            ],
            "uid": [
                {
                    "target_id": 2
                }
            ],
            "filename": [
                {
                    "value": "card-image-steps_1.png"
                }
            ],
            "uri": [
                {
                    "value": "public:\/\/2020-03\/card-image-steps_1.png",
                    "url": "\/sites\/default\/files\/2020-03\/card-image-steps_1.png"
                }
            ],
            "filemime": [
                {
                    "value": "image\/png"
                }
            ],
            "filesize": [
                {
                    "value": 76218
                }
            ],
            "status": [
                {
                    "value": true
                }
            ],
            "created": [
                {
                    "value": "2020-03-15T21:30:41+00:00",
                    "format": "Y-m-d\\TH:i:sP"
                }
            ],
            "changed": [
                {
                    "value": "2020-03-15T21:30:44+00:00",
                    "format": "Y-m-d\\TH:i:sP"
                }
            ]
        },
        {
            "fid": [
                {
                    "value": 11
                }
            ],
            "uuid": [
                {
                    "value": "b0fa5186-efdd-4c32-b802-07ee4a13a416"
                }
            ],
            "langcode": [
                {
                    "value": "en"
                }
            ],
            "uid": [
                {
                    "target_id": 2
                }
            ],
            "filename": [
                {
                    "value": "card-image-lactation_1.png"
                }
            ],
            "uri": [
                {
                    "value": "public:\/\/2020-03\/card-image-lactation_1.png",
                    "url": "\/sites\/default\/files\/2020-03\/card-image-lactation_1.png"
                }
            ],
            "filemime": [
                {
                    "value": "image\/png"
                }
            ],
            "filesize": [
                {
                    "value": 129978
                }
            ],
            "status": [
                {
                    "value": true
                }
            ],
            "created": [
                {
                    "value": "2020-03-15T21:30:54+00:00",
                    "format": "Y-m-d\\TH:i:sP"
                }
            ],
            "changed": [
                {
                    "value": "2020-03-15T21:30:57+00:00",
                    "format": "Y-m-d\\TH:i:sP"
                }
            ]
        },
        {
            "fid": [
                {
                    "value": 12
                }
            ],
            "uuid": [
                {
                    "value": "de2a3dc5-a9c0-4388-8e1a-7e9bbaf4b899"
                }
            ],
            "langcode": [
                {
                    "value": "en"
                }
            ],
            "uid": [
                {
                    "target_id": 2
                }
            ],
            "filename": [
                {
                    "value": "card-image-cal-optima_1.png"
                }
            ],
            "uri": [
                {
                    "value": "public:\/\/2020-03\/card-image-cal-optima_1.png",
                    "url": "\/sites\/default\/files\/2020-03\/card-image-cal-optima_1.png"
                }
            ],
            "filemime": [
                {
                    "value": "image\/png"
                }
            ],
            "filesize": [
                {
                    "value": 141781
                }
            ],
            "status": [
                {
                    "value": true
                }
            ],
            "created": [
                {
                    "value": "2020-03-15T21:31:09+00:00",
                    "format": "Y-m-d\\TH:i:sP"
                }
            ],
            "changed": [
                {
                    "value": "2020-03-15T21:31:11+00:00",
                    "format": "Y-m-d\\TH:i:sP"
                }
            ]
        },
        {
            "fid": [
                {
                    "value": 13
                }
            ],
            "uuid": [
                {
                    "value": "40924646-7bb6-42c0-aab3-bc03e3ddd066"
                }
            ],
            "langcode": [
                {
                    "value": "en"
                }
            ],
            "uid": [
                {
                    "target_id": 7231318
                }
            ],
            "filename": [
                {
                    "value": "HumanCapital1-sidewalk_1680x999.png"
                }
            ],
            "uri": [
                {
                    "value": "public:\/\/2020-03\/HumanCapital1-sidewalk_1680x999.png",
                    "url": "\/sites\/default\/files\/2020-03\/HumanCapital1-sidewalk_1680x999.png"
                }
            ],
            "filemime": [
                {
                    "value": "image\/png"
                }
            ],
            "filesize": [
                {
                    "value": 2508257
                }
            ],
            "status": [
                {
                    "value": true
                }
            ],
            "created": [
                {
                    "value": "2020-03-20T20:15:53+00:00",
                    "format": "Y-m-d\\TH:i:sP"
                }
            ],
            "changed": [
                {
                    "value": "2020-03-20T20:16:28+00:00",
                    "format": "Y-m-d\\TH:i:sP"
                }
            ]
        },
        {
            "fid": [
                {
                    "value": 14
                }
            ],
            "uuid": [
                {
                    "value": "e4e2e4e6-889f-4034-9ca8-a9500936aad9"
                }
            ],
            "langcode": [
                {
                    "value": "en"
                }
            ],
            "uid": [
                {
                    "target_id": 7231318
                }
            ],
            "filename": [
                {
                    "value": "Approrpiations Law@2x.png"
                }
            ],
            "uri": [
                {
                    "value": "public:\/\/2020-03\/Approrpiations Law@2x.png",
                    "url": "\/sites\/default\/files\/2020-03\/Approrpiations%20Law%402x.png"
                }
            ],
            "filemime": [
                {
                    "value": "image\/png"
                }
            ],
            "filesize": [
                {
                    "value": 503061
                }
            ],
            "status": [
                {
                    "value": true
                }
            ],
            "created": [
                {
                    "value": "2020-03-20T20:17:40+00:00",
                    "format": "Y-m-d\\TH:i:sP"
                }
            ],
            "changed": [
                {
                    "value": "2020-03-20T20:18:19+00:00",
                    "format": "Y-m-d\\TH:i:sP"
                }
            ]
        },
        {
            "fid": [
                {
                    "value": 15
                }
            ],
            "uuid": [
                {
                    "value": "fe67ec5a-4f0a-4bb6-b428-d819c2763d29"
                }
            ],
            "langcode": [
                {
                    "value": "en"
                }
            ],
            "uid": [
                {
                    "target_id": 37
                }
            ],
            "filename": [
                {
                    "value": "logo-occ-banner.png"
                }
            ],
            "uri": [
                {
                    "value": "public:\/\/2020-04\/logo-occ-banner.png",
                    "url": "\/sites\/default\/files\/2020-04\/logo-occ-banner.png"
                }
            ],
            "filemime": [
                {
                    "value": "image\/png"
                }
            ],
            "filesize": [
                {
                    "value": 143449
                }
            ],
            "status": [
                {
                    "value": true
                }
            ],
            "created": [
                {
                    "value": "2020-04-14T20:28:25+00:00",
                    "format": "Y-m-d\\TH:i:sP"
                }
            ],
            "changed": [
                {
                    "value": "2020-04-14T20:28:40+00:00",
                    "format": "Y-m-d\\TH:i:sP"
                }
            ]
        },
        {
            "fid": [
                {
                    "value": 16
                }
            ],
            "uuid": [
                {
                    "value": "b5df20a9-3cae-4260-844e-e92e957b12c8"
                }
            ],
            "langcode": [
                {
                    "value": "en"
                }
            ],
            "uid": [
                {
                    "target_id": 64253346
                }
            ],
            "filename": [
                {
                    "value": "Laguna-Beach-California.jpg"
                }
            ],
            "uri": [
                {
                    "value": "public:\/\/2020-04\/Laguna-Beach-California.jpg",
                    "url": "\/sites\/default\/files\/2020-04\/Laguna-Beach-California.jpg"
                }
            ],
            "filemime": [
                {
                    "value": "image\/jpeg"
                }
            ],
            "filesize": [
                {
                    "value": 385619
                }
            ],
            "status": [
                {
                    "value": true
                }
            ],
            "created": [
                {
                    "value": "2020-04-14T19:36:04+00:00",
                    "format": "Y-m-d\\TH:i:sP"
                }
            ],
            "changed": [
                {
                    "value": "2020-04-14T19:36:14+00:00",
                    "format": "Y-m-d\\TH:i:sP"
                }
            ]
        },
        {
            "fid": [
                {
                    "value": 17
                }
            ],
            "uuid": [
                {
                    "value": "28f43cf3-a45c-4b2e-9b21-2779154ec27d"
                }
            ],
            "langcode": [
                {
                    "value": "en"
                }
            ],
            "uid": [
                {
                    "target_id": 3
                }
            ],
            "filename": [
                {
                    "value": "ocanimalcare.jpeg"
                }
            ],
            "uri": [
                {
                    "value": "public:\/\/2020-05\/ocanimalcare.jpeg",
                    "url": "\/sites\/default\/files\/2020-05\/ocanimalcare.jpeg"
                }
            ],
            "filemime": [
                {
                    "value": "image\/jpeg"
                }
            ],
            "filesize": [
                {
                    "value": 12688
                }
            ],
            "status": [
                {
                    "value": true
                }
            ],
            "created": [
                {
                    "value": "2020-05-08T13:21:18+00:00",
                    "format": "Y-m-d\\TH:i:sP"
                }
            ],
            "changed": [
                {
                    "value": "2020-05-08T13:23:12+00:00",
                    "format": "Y-m-d\\TH:i:sP"
                }
            ]
        },
        {
            "fid": [
                {
                    "value": 18
                }
            ],
            "uuid": [
                {
                    "value": "83515b32-dbf4-43d8-97b7-7103ceeddd01"
                }
            ],
            "langcode": [
                {
                    "value": "en"
                }
            ],
            "uid": [
                {
                    "target_id": 3
                }
            ],
            "filename": [
                {
                    "value": "generic.png"
                }
            ],
            "uri": [
                {
                    "value": "public:\/\/media-icons\/generic\/generic.png",
                    "url": "\/sites\/default\/files\/media-icons\/generic\/generic.png"
                }
            ],
            "filemime": [
                {
                    "value": "image\/png"
                }
            ],
            "filesize": [
                {
                    "value": 3900
                }
            ],
            "status": [
                {
                    "value": true
                }
            ],
            "created": [
                {
                    "value": "2020-05-08T13:25:29+00:00",
                    "format": "Y-m-d\\TH:i:sP"
                }
            ],
            "changed": [
                {
                    "value": "2020-05-08T13:25:29+00:00",
                    "format": "Y-m-d\\TH:i:sP"
                }
            ]
        },
        {
            "fid": [
                {
                    "value": 19
                }
            ],
            "uuid": [
                {
                    "value": "90b9c962-58aa-461e-9dce-f40d35ed4565"
                }
            ],
            "langcode": [
                {
                    "value": "en"
                }
            ],
            "uid": [
                {
                    "target_id": 3
                }
            ],
            "filename": [
                {
                    "value": "4077.pdf"
                }
            ],
            "uri": [
                {
                    "value": "public:\/\/2020-05\/4077_1.pdf",
                    "url": "\/sites\/default\/files\/2020-05\/4077_1.pdf"
                }
            ],
            "filemime": [
                {
                    "value": "application\/pdf"
                }
            ],
            "filesize": [
                {
                    "value": 6997031
                }
            ],
            "status": [
                {
                    "value": true
                }
            ],
            "created": [
                {
                    "value": "2020-05-08T13:49:40+00:00",
                    "format": "Y-m-d\\TH:i:sP"
                }
            ],
            "changed": [
                {
                    "value": "2020-05-08T13:49:44+00:00",
                    "format": "Y-m-d\\TH:i:sP"
                }
            ]
        },
        {
            "fid": [
                {
                    "value": 20
                }
            ],
            "uuid": [
                {
                    "value": "98222d1f-e8a0-41d9-bbb3-ec1ee2b9acc2"
                }
            ],
            "langcode": [
                {
                    "value": "en"
                }
            ],
            "uid": [
                {
                    "target_id": 3
                }
            ],
            "filename": [
                {
                    "value": "4080.pdf"
                }
            ],
            "uri": [
                {
                    "value": "public:\/\/2020-05\/4080_1.pdf",
                    "url": "\/sites\/default\/files\/2020-05\/4080_1.pdf"
                }
            ],
            "filemime": [
                {
                    "value": "application\/pdf"
                }
            ],
            "filesize": [
                {
                    "value": 5863774
                }
            ],
            "status": [
                {
                    "value": true
                }
            ],
            "created": [
                {
                    "value": "2020-05-08T13:49:40+00:00",
                    "format": "Y-m-d\\TH:i:sP"
                }
            ],
            "changed": [
                {
                    "value": "2020-05-08T13:49:44+00:00",
                    "format": "Y-m-d\\TH:i:sP"
                }
            ]
        },
        {
            "fid": [
                {
                    "value": 21
                }
            ],
            "uuid": [
                {
                    "value": "609337e9-f12c-491d-b5f9-8899f6d588ff"
                }
            ],
            "langcode": [
                {
                    "value": "en"
                }
            ],
            "uid": [
                {
                    "target_id": 3
                }
            ],
            "filename": [
                {
                    "value": "4079.pdf"
                }
            ],
            "uri": [
                {
                    "value": "public:\/\/2020-05\/4079_1.pdf",
                    "url": "\/sites\/default\/files\/2020-05\/4079_1.pdf"
                }
            ],
            "filemime": [
                {
                    "value": "application\/pdf"
                }
            ],
            "filesize": [
                {
                    "value": 30515
                }
            ],
            "status": [
                {
                    "value": true
                }
            ],
            "created": [
                {
                    "value": "2020-05-08T13:49:40+00:00",
                    "format": "Y-m-d\\TH:i:sP"
                }
            ],
            "changed": [
                {
                    "value": "2020-05-08T13:49:44+00:00",
                    "format": "Y-m-d\\TH:i:sP"
                }
            ]
        },
        {
            "fid": [
                {
                    "value": 22
                }
            ],
            "uuid": [
                {
                    "value": "266e17ed-ed97-4192-99c9-373db3323f07"
                }
            ],
            "langcode": [
                {
                    "value": "en"
                }
            ],
            "uid": [
                {
                    "target_id": 0,
                    "target_type": "user",
                    "target_uuid": "cf24bc86-c86a-4c46-a0da-a76a72c3654b",
                    "url": "\/user\/0"
                }
            ],
            "filename": [
                {
                    "value": "me5.jpg"
                }
            ],
            "uri": [
                {
                    "value": "public:\/\/2020-09\/me5.jpg",
                    "url": "\/sites\/default\/files\/2020-09\/me5.jpg"
                }
            ],
            "filemime": [
                {
                    "value": "image\/jpeg"
                }
            ],
            "filesize": [
                {
                    "value": 1113831
                }
            ],
            "status": [
                {
                    "value": true
                }
            ],
            "created": [
                {
                    "value": "2020-09-18T01:55:38+00:00",
                    "format": "Y-m-d\\TH:i:sP"
                }
            ],
            "changed": [
                {
                    "value": "2020-09-18T01:55:42+00:00",
                    "format": "Y-m-d\\TH:i:sP"
                }
            ]
        },
        {
            "fid": [
                {
                    "value": 23
                }
            ],
            "uuid": [
                {
                    "value": "07be6c72-1170-4e65-b4c9-956c710d09d4"
                }
            ],
            "langcode": [
                {
                    "value": "en"
                }
            ],
            "uid": [
                {
                    "target_id": 0,
                    "target_type": "user",
                    "target_uuid": "cf24bc86-c86a-4c46-a0da-a76a72c3654b",
                    "url": "\/user\/0"
                }
            ],
            "filename": [
                {
                    "value": "jane-doe.png"
                }
            ],
            "uri": [
                {
                    "value": "public:\/\/2020-09\/jane-doe.png",
                    "url": "\/sites\/default\/files\/2020-09\/jane-doe.png"
                }
            ],
            "filemime": [
                {
                    "value": "image\/png"
                }
            ],
            "filesize": [
                {
                    "value": 1173590
                }
            ],
            "status": [
                {
                    "value": true
                }
            ],
            "created": [
                {
                    "value": "2020-09-18T01:57:54+00:00",
                    "format": "Y-m-d\\TH:i:sP"
                }
            ],
            "changed": [
                {
                    "value": "2020-09-18T01:58:00+00:00",
                    "format": "Y-m-d\\TH:i:sP"
                }
            ]
        },
        {
            "fid": [
                {
                    "value": 24
                }
            ],
            "uuid": [
                {
                    "value": "03020461-c46b-4c64-8ac3-582cc38f2161"
                }
            ],
            "langcode": [
                {
                    "value": "en"
                }
            ],
            "uid": [
                {
                    "target_id": 1,
                    "target_type": "user",
                    "target_uuid": "b7db48a7-0ee6-475e-bd3f-d88e2075bc2e",
                    "url": "\/user\/1"
                }
            ],
            "filename": [
                {
                    "value": "generateImage_Vsi6QH.gif"
                }
            ],
            "uri": [
                {
                    "value": "public:\/\/2020-09\/generateImage_Vsi6QH.gif",
                    "url": "\/sites\/default\/files\/2020-09\/generateImage_Vsi6QH.gif"
                }
            ],
            "filemime": [
                {
                    "value": "image\/gif"
                }
            ],
            "filesize": [
                {
                    "value": 2645
                }
            ],
            "status": [
                {
                    "value": false
                }
            ],
            "created": [
                {
                    "value": "2020-09-18T15:03:52+00:00",
                    "format": "Y-m-d\\TH:i:sP"
                }
            ],
            "changed": [
                {
                    "value": "2020-09-18T15:03:52+00:00",
                    "format": "Y-m-d\\TH:i:sP"
                }
            ]
        },
        {
            "fid": [
                {
                    "value": 25
                }
            ],
            "uuid": [
                {
                    "value": "254d7f7a-e367-4489-8062-045dfc6e0023"
                }
            ],
            "langcode": [
                {
                    "value": "en"
                }
            ],
            "uid": [
                {
                    "target_id": 1,
                    "target_type": "user",
                    "target_uuid": "b7db48a7-0ee6-475e-bd3f-d88e2075bc2e",
                    "url": "\/user\/1"
                }
            ],
            "filename": [
                {
                    "value": "ue5fIC8tdM.txt"
                }
            ],
            "uri": [
                {
                    "value": "public:\/\/2020-09\/ue5fIC8tdM.txt",
                    "url": "\/sites\/default\/files\/2020-09\/ue5fIC8tdM.txt"
                }
            ],
            "filemime": [
                {
                    "value": "text\/plain"
                }
            ],
            "filesize": [
                {
                    "value": 768
                }
            ],
            "status": [
                {
                    "value": true
                }
            ],
            "created": [
                {
                    "value": "2020-09-18T15:03:52+00:00",
                    "format": "Y-m-d\\TH:i:sP"
                }
            ],
            "changed": [
                {
                    "value": "2020-09-18T15:03:52+00:00",
                    "format": "Y-m-d\\TH:i:sP"
                }
            ]
        },
        {
            "fid": [
                {
                    "value": 26
                }
            ],
            "uuid": [
                {
                    "value": "c58aa5bd-0832-401c-aa8a-29fc3e33d93a"
                }
            ],
            "langcode": [
                {
                    "value": "en"
                }
            ],
            "uid": [
                {
                    "target_id": 1,
                    "target_type": "user",
                    "target_uuid": "b7db48a7-0ee6-475e-bd3f-d88e2075bc2e",
                    "url": "\/user\/1"
                }
            ],
            "filename": [
                {
                    "value": "8140915107_f94a7dcfcd_o.jpg"
                }
            ],
            "uri": [
                {
                    "value": "public:\/\/2020-09\/8140915107_f94a7dcfcd_o.jpg",
                    "url": "\/sites\/default\/files\/2020-09\/8140915107_f94a7dcfcd_o.jpg"
                }
            ],
            "filemime": [
                {
                    "value": "image\/jpeg"
                }
            ],
            "filesize": [
                {
                    "value": 650520
                }
            ],
            "status": [
                {
                    "value": true
                }
            ],
            "created": [
                {
                    "value": "2020-09-18T15:10:39+00:00",
                    "format": "Y-m-d\\TH:i:sP"
                }
            ],
            "changed": [
                {
                    "value": "2020-09-18T15:10:45+00:00",
                    "format": "Y-m-d\\TH:i:sP"
                }
            ]
        },
        {
            "fid": [
                {
                    "value": 27
                }
            ],
            "uuid": [
                {
                    "value": "0a7f5dfb-f244-4cea-9948-6cb0c315434b"
                }
            ],
            "langcode": [
                {
                    "value": "en"
                }
            ],
            "uid": [
                {
                    "target_id": 1,
                    "target_type": "user",
                    "target_uuid": "b7db48a7-0ee6-475e-bd3f-d88e2075bc2e",
                    "url": "\/user\/1"
                }
            ],
            "filename": [
                {
                    "value": "southport-county-courthouse11_2.jpg"
                }
            ],
            "uri": [
                {
                    "value": "public:\/\/2020-09\/southport-county-courthouse11_2.jpg",
                    "url": "\/sites\/default\/files\/2020-09\/southport-county-courthouse11_2.jpg"
                }
            ],
            "filemime": [
                {
                    "value": "image\/jpeg"
                }
            ],
            "filesize": [
                {
                    "value": 343016
                }
            ],
            "status": [
                {
                    "value": true
                }
            ],
            "created": [
                {
                    "value": "2020-09-18T15:10:56+00:00",
                    "format": "Y-m-d\\TH:i:sP"
                }
            ],
            "changed": [
                {
                    "value": "2020-09-18T15:10:59+00:00",
                    "format": "Y-m-d\\TH:i:sP"
                }
            ]
        },
        {
            "fid": [
                {
                    "value": 28
                }
            ],
            "uuid": [
                {
                    "value": "3f4c7fe5-12b8-4b33-beae-dfacc0b39349"
                }
            ],
            "langcode": [
                {
                    "value": "en"
                }
            ],
            "uid": [
                {
                    "target_id": 1,
                    "target_type": "user",
                    "target_uuid": "b7db48a7-0ee6-475e-bd3f-d88e2075bc2e",
                    "url": "\/user\/1"
                }
            ],
            "filename": [
                {
                    "value": "logo-southport-banner.png"
                }
            ],
            "uri": [
                {
                    "value": "public:\/\/2020-09\/logo-southport-banner.png",
                    "url": "\/sites\/default\/files\/2020-09\/logo-southport-banner.png"
                }
            ],
            "filemime": [
                {
                    "value": "image\/png"
                }
            ],
            "filesize": [
                {
                    "value": 6841
                }
            ],
            "status": [
                {
                    "value": true
                }
            ],
            "created": [
                {
                    "value": "2020-09-18T15:11:29+00:00",
                    "format": "Y-m-d\\TH:i:sP"
                }
            ],
            "changed": [
                {
                    "value": "2020-09-18T15:11:35+00:00",
                    "format": "Y-m-d\\TH:i:sP"
                }
            ]
        },
        {
            "fid": [
                {
                    "value": 29
                }
            ],
            "uuid": [
                {
                    "value": "332593ae-f635-4d24-aec8-f9393c47a5d5"
                }
            ],
            "langcode": [
                {
                    "value": "en"
                }
            ],
            "uid": [
                {
                    "target_id": 1,
                    "target_type": "user",
                    "target_uuid": "b7db48a7-0ee6-475e-bd3f-d88e2075bc2e",
                    "url": "\/user\/1"
                }
            ],
            "filename": [
                {
                    "value": "vlads background.jpeg"
                }
            ],
            "uri": [
                {
                    "value": "public:\/\/2020-09\/vlads background.jpeg",
                    "url": "\/sites\/default\/files\/2020-09\/vlads%20background.jpeg"
                }
            ],
            "filemime": [
                {
                    "value": "image\/jpeg"
                }
            ],
            "filesize": [
                {
                    "value": 135576
                }
            ],
            "status": [
                {
                    "value": true
                }
            ],
            "created": [
                {
                    "value": "2020-09-18T15:13:03+00:00",
                    "format": "Y-m-d\\TH:i:sP"
                }
            ],
            "changed": [
                {
                    "value": "2020-09-18T15:13:07+00:00",
                    "format": "Y-m-d\\TH:i:sP"
                }
            ]
        },
        {
            "fid": [
                {
                    "value": 30
                }
            ],
            "uuid": [
                {
                    "value": "ed819068-cc84-48a9-a01d-c02ad3efc6ad"
                }
            ],
            "langcode": [
                {
                    "value": "en"
                }
            ],
            "uid": [
                {
                    "target_id": 1,
                    "target_type": "user",
                    "target_uuid": "b7db48a7-0ee6-475e-bd3f-d88e2075bc2e",
                    "url": "\/user\/1"
                }
            ],
            "filename": [
                {
                    "value": "wheelercolor.jpg"
                }
            ],
            "uri": [
                {
                    "value": "public:\/\/2020-09\/wheelercolor.jpg",
                    "url": "\/sites\/default\/files\/2020-09\/wheelercolor.jpg"
                }
            ],
            "filemime": [
                {
                    "value": "image\/jpeg"
                }
            ],
            "filesize": [
                {
                    "value": 153977
                }
            ],
            "status": [
                {
                    "value": true
                }
            ],
            "created": [
                {
                    "value": "2020-09-18T15:13:53+00:00",
                    "format": "Y-m-d\\TH:i:sP"
                }
            ],
            "changed": [
                {
                    "value": "2020-09-18T15:13:57+00:00",
                    "format": "Y-m-d\\TH:i:sP"
                }
            ]
        },
        {
            "fid": [
                {
                    "value": 31
                }
            ],
            "uuid": [
                {
                    "value": "2b64f334-7f44-4554-9226-df7a30a0b76f"
                }
            ],
            "langcode": [
                {
                    "value": "en"
                }
            ],
            "uid": [
                {
                    "target_id": 1,
                    "target_type": "user",
                    "target_uuid": "b7db48a7-0ee6-475e-bd3f-d88e2075bc2e",
                    "url": "\/user\/1"
                }
            ],
            "filename": [
                {
                    "value": "x093x-veterans-memorial-bridge-palm-city-florida.jpg"
                }
            ],
            "uri": [
                {
                    "value": "public:\/\/2020-09\/x093x-veterans-memorial-bridge-palm-city-florida.jpg",
                    "url": "\/sites\/default\/files\/2020-09\/x093x-veterans-memorial-bridge-palm-city-florida.jpg"
                }
            ],
            "filemime": [
                {
                    "value": "image\/jpeg"
                }
            ],
            "filesize": [
                {
                    "value": 141776
                }
            ],
            "status": [
                {
                    "value": true
                }
            ],
            "created": [
                {
                    "value": "2020-09-18T15:15:34+00:00",
                    "format": "Y-m-d\\TH:i:sP"
                }
            ],
            "changed": [
                {
                    "value": "2020-09-18T15:15:46+00:00",
                    "format": "Y-m-d\\TH:i:sP"
                }
            ]
        }
    ]
}